{
    "name": "Pot!on",
    "logo": "config/potion/potion.jpg",
    "font": "ancient",
    "links": [
        {
            "name": "Youtube",
            "service": "Youtube",
            "link": "https://www.youtube.com/channel/UCdnKkw5D0ZEzRP01b73t2Ng"
        },
        {
            "name": "SoundCloud",
            "service": "Soundcloud",
            "link": "https://soundcloud.com/user-357305126-160770071"
        },
        {
            "name": "Instagram",
            "service": "Instagram",
            "link": "https://youtube.com"
        },
        {
            "name": "Discord",
            "service": "Discord",
            "link": "https://discord.com/invite/rd4RgWJGzA"
        },
        {
            "name": "Bandcamp",
            "service": "Bandcamp",
            "link": "https://drinkpotion.bandcamp.com/releases"
        }
    ]
}